{
  "name": "Buckram Leggings",
  "type": "armorgear",
  "img": "systems/hm3/images/icons/svg/leggings.svg",
  "effects": [],
  "folder": null,
  "sort": 0,
  "flags": {},
  "_id": "eFMSHOjpZg0pE8gt",
  "system": {
    "notes": "",
    "description": "",
    "source": "",
    "macros": {
      "type": "script",
      "command": ""
    },
    "quantity": 1,
    "value": 69,
    "weight": 4.4,
    "isCarried": true,
    "isEquipped": true,
    "container": "on-person",
    "arcane": {
      "isArtifact": false,
      "isAttuned": false,
      "charges": -1,
      "ego": 0
    },
    "material": "Cloth",
    "armorQuality": 0,
    "locations": [
      "Hip",
      "Groin",
      "Thigh",
      "Knee",
      "Calf",
      "Foot"
    ],
    "protection": {
      "blunt": 1,
      "edged": 1,
      "piercing": 1,
      "fire": 1
    },
    "size": 6
  },
  "ownership": {
    "default": 0,
    "di0AAKiFfyeVymgl": 3
  },
  "_stats": {
    "systemId": null,
    "systemVersion": null,
    "coreVersion": null,
    "createdTime": null,
    "modifiedTime": null,
    "lastModifiedBy": null
  },
  "_key": "!actors!eFMSHOjpZg0pE8gt"
}
